glin_profanity/__init__.py
glin_profanity/data/__init__.py
glin_profanity/data/dictionary.py
glin_profanity/data/dictionaries/arabic.json
glin_profanity/data/dictionaries/chinese.json
glin_profanity/data/dictionaries/czech.json
glin_profanity/data/dictionaries/danish.json
glin_profanity/data/dictionaries/dutch.json
glin_profanity/data/dictionaries/english.json
glin_profanity/data/dictionaries/esperanto.json
glin_profanity/data/dictionaries/finnish.json
glin_profanity/data/dictionaries/french.json
glin_profanity/data/dictionaries/german.json
glin_profanity/data/dictionaries/globalWhitelist.json
glin_profanity/data/dictionaries/hindi.json
glin_profanity/data/dictionaries/hungarian.json
glin_profanity/data/dictionaries/italian.json
glin_profanity/data/dictionaries/japanese.json
glin_profanity/data/dictionaries/korean.json
glin_profanity/data/dictionaries/norwegian.json
glin_profanity/data/dictionaries/persian.json
glin_profanity/data/dictionaries/polish.json
glin_profanity/data/dictionaries/portuguese.json
glin_profanity/data/dictionaries/russian.json
glin_profanity/data/dictionaries/spanish.json
glin_profanity/data/dictionaries/swedish.json
glin_profanity/data/dictionaries/thai.json
glin_profanity/data/dictionaries/turkish.json
glin_profanity/filters/__init__.py
glin_profanity/filters/filter.py
glin_profanity/ml/__init__.py
glin_profanity/ml/hybrid.py
glin_profanity/ml/lightweight.py
glin_profanity/ml/toxicity.py
glin_profanity/ml/types.py
glin_profanity/nlp/__init__.py
glin_profanity/types/__init__.py
glin_profanity/types/types.py
glin_profanity/utils/__init__.py
glin_profanity/utils/leetspeak.py
glin_profanity/utils/unicode.py
glin_profanity-3.3.0.dist-info/METADATA
glin_profanity-3.3.0.dist-info/WHEEL
glin_profanity-3.3.0.dist-info/RECORD
