Metadata-Version: 2.4
Name: glin-profanity
Version: 3.3.0
Summary: Glin-Profanity is a lightweight and efficient Python package designed to detect and filter profane language in text inputs across multiple languages.
Project-URL: Homepage, https://www.glincker.com/tools/glin-profanity
Project-URL: Documentation, https://github.com/GLINCKER/glin-profanity
Project-URL: Repository, https://github.com/GLINCKER/glin-profanity
Project-URL: Issues, https://github.com/GLINCKER/glin-profanity/issues
Author-email: glinr <contact@glincker.com>
Maintainer-email: glinr <contact@glincker.com>
License-Expression: MIT
Keywords: bert,censorship,chat,comment,content,detection,filter,glin,glincker,homoglyph,language,leetspeak,machine-learning,ml,moderation,nlp,profanity,social,text,toxicity,transformer,unicode
Classifier: Development Status :: 5 - Production/Stable
Classifier: Intended Audience :: Developers
Classifier: License :: OSI Approved :: MIT License
Classifier: Operating System :: OS Independent
Classifier: Programming Language :: Python :: 3
Classifier: Programming Language :: Python :: 3.10
Classifier: Programming Language :: Python :: 3.11
Classifier: Programming Language :: Python :: 3.12
Classifier: Topic :: Internet :: WWW/HTTP :: Dynamic Content
Classifier: Topic :: Software Development :: Libraries :: Python Modules
Classifier: Topic :: Text Processing :: Filters
Requires-Python: >=3.10
Requires-Dist: typing-extensions>=4.0.0
Provides-Extra: dev
Requires-Dist: black>=23.0.0; extra == 'dev'
Requires-Dist: isort>=5.0.0; extra == 'dev'
Requires-Dist: mypy>=1.0.0; extra == 'dev'
Requires-Dist: pytest-cov>=4.0.0; extra == 'dev'
Requires-Dist: pytest>=7.0.0; extra == 'dev'
Requires-Dist: ruff>=0.1.0; extra == 'dev'
Provides-Extra: ml
Requires-Dist: detoxify>=0.5.0; extra == 'ml'
Requires-Dist: profanity-check>=1.0.0; extra == 'ml'
Requires-Dist: torch>=2.0.0; extra == 'ml'
Provides-Extra: ml-lightweight
Requires-Dist: profanity-check>=1.0.0; extra == 'ml-lightweight'
Provides-Extra: ml-transformer
Requires-Dist: detoxify>=0.5.0; extra == 'ml-transformer'
Requires-Dist: torch>=2.0.0; extra == 'ml-transformer'
Provides-Extra: test
Requires-Dist: pytest-cov>=4.0.0; extra == 'test'
Requires-Dist: pytest>=7.0.0; extra == 'test'
